simdjson_schemaful/__init__.py
simdjson_schemaful/__version__.py
simdjson_schemaful/parser.py
simdjson_schemaful/py.typed
simdjson_schemaful/pydantic/__init__.py
simdjson_schemaful/pydantic/v1.py
simdjson_schemaful/pydantic/v2.py
pysimdjson_schemaful-0.3.0.dist-info/LICENSE
pysimdjson_schemaful-0.3.0.dist-info/METADATA
pysimdjson_schemaful-0.3.0.dist-info/WHEEL
pysimdjson_schemaful-0.3.0.dist-info/RECORD
