Metadata-Version: 2.1
Name: pysimdjson-schemaful
Version: 0.3.0
Summary: Schema-aware pysimdjson loader for efficient parsing of large excessive inputs.
Home-page: https://github.com/tzoiker/pysimdjson-schemaful
License: MIT
Author: Tzoiker
Author-email: tzoiker@gmail.com
Requires-Python: >=3.8,<3.13
Classifier: Development Status :: 2 - Pre-Alpha
Classifier: Intended Audience :: Developers
Classifier: Intended Audience :: Information Technology
Classifier: License :: OSI Approved :: MIT License
Classifier: Natural Language :: English
Classifier: Operating System :: POSIX :: Linux
Classifier: Programming Language :: Python
Classifier: Programming Language :: Python :: 3
Classifier: Programming Language :: Python :: 3.8
Classifier: Programming Language :: Python :: 3.9
Classifier: Programming Language :: Python :: 3.10
Classifier: Programming Language :: Python :: 3.11
Classifier: Programming Language :: Python :: 3.12
Classifier: Programming Language :: Python :: Implementation :: CPython
Classifier: Topic :: Internet
Classifier: Topic :: Software Development
Classifier: Topic :: Software Development :: Libraries
Classifier: Topic :: Software Development :: Libraries :: Python Modules
Classifier: Topic :: Utilities
Classifier: Typing :: Typed
Provides-Extra: pydantic
Requires-Dist: pydantic (>=1,<3) ; extra == "pydantic"
Requires-Dist: pysimdjson (>=2,<7) ; python_version >= "3.8" and python_version < "3.9"
Requires-Dist: pysimdjson (>=3,!=4.*,<7) ; python_version >= "3.11" and python_version < "3.12"
Requires-Dist: pysimdjson (>=3,<7) ; python_version >= "3.9" and python_version < "3.11"
Requires-Dist: pysimdjson (>=6,<7) ; python_version >= "3.12" and python_version < "3.13"
Project-URL: Repository, https://github.com/tzoiker/pysimdjson-schemaful
